{"type": "FeatureCollection", "features": [{"geometry": {"type": "Point", "coordinates": [-69.2254226135862, 18.792560147808395]}, "type": "Feature", "properties": {"Coordenada": 476245, "AquiferID": 2, "Coordena_1": 2077890, "HydroID": "0", "LandElev": -9999}}, {"geometry": {"type": "Point", "coordinates": [-69.23775481569332, 18.78966178749817]}, "type": "Feature", "properties": {"Coordenada": 474945, "AquiferID": 2, "Coordena_1": 2077571, "HydroID": "0", "LandElev": -9999}}, {"geometry": {"type": "Point", "coordinates": [-69.159295365498, 18.706632635891168]}, "type": "Feature", "properties": {"Coordenada": 483205, "AquiferID": 2, "Coordena_1": 2068375, "HydroID": "0", "LandElev": -9999}}, {"geometry": {"type": "Point", "coordinates": [-69.14149031012852, 18.81763226638097]}, "type": "Feature", "properties": {"Coordenada": 485092, "AquiferID": 2, "Coordena_1": 2080655, "HydroID": "0", "LandElev": -9999}}, {"geometry": {"type": "Point", "coordinates": [-69.28668974711957, 18.74967303591318]}, "type": "Feature", "properties": {"Coordenada": 469781, "AquiferID": 2, "Coordena_1": 2073154, "HydroID": "0", "LandElev": -9999}}, {"geometry": {"type": "Point", "coordinates": [-69.15927904865445, 18.840781868091426]}, "type": "Feature", "properties": {"Coordenada": 483220, "AquiferID": 2, "Coordena_1": 2083218, "HydroID": "0", "LandElev": -9999}}, {"geometry": {"type": "Point", "coordinates": [-68.85907574314824, 18.650114808178998]}, "type": "Feature", "properties": {"Coordenada": 514863, "AquiferID": 2, "Coordena_1": 2062120, "HydroID": "6174420005", "LandElev": -9999}}, {"geometry": {"type": "Point", "coordinates": [-69.5007219388531, 18.813181934317313]}, "type": "Feature", "properties": {"Coordenada": 447240, "AquiferID": 2, "Coordena_1": 2080231, "HydroID": "6272230001", "LandElev": -9999}}, {"TsValue": [-9.02, -8.0], "TsTime": [1060905600, 1066867200], "geometry": {"type": "Point", "coordinates": [-69.17933521550572, 18.750412267571182]}, "TsValue_norm": [-9.02, -8.0], "type": "Feature", "properties": {"Coordenada": 481097, "AquiferID": 2, "Coordena_1": 2073221, "HydroID": "6273210034", "LandElev": -9999}}, {"geometry": {"type": "Point", "coordinates": [-69.15096690178703, 18.6413130327152]}, "type": "Feature", "properties": {"Coordenada": 484077, "AquiferID": 2, "Coordena_1": 2061147, "HydroID": "6371120001", "LandElev": -9999}}, {"geometry": {"type": "Point", "coordinates": [-69.04009054420355, 18.981175096273994]}, "type": "Feature", "properties": {"Coordenada": 495780, "AquiferID": 2, "Coordena_1": 2098745, "HydroID": "6371130001", "LandElev": -9999}}, {"TsValue": [-24.27, -23.97, -23.86, -21.9], "TsTime": [1060905600, 1066953600, 1068595200, 1196812800], "geometry": {"type": "Point", "coordinates": [-69.16563654689477, 18.682947707779977]}, "TsValue_norm": [-24.27, -23.97, -23.86, -21.9], "type": "Feature", "properties": {"Coordenada": 482534, "AquiferID": 2, "Coordena_1": 2065755, "HydroID": "6371150002", "LandElev": -9999}}, {"geometry": {"type": "Point", "coordinates": [-69.14888584827722, 18.668537134682403]}, "type": "Feature", "properties": {"Coordenada": 484299, "AquiferID": 2, "Coordena_1": 2064159, "HydroID": "6372", "LandElev": -9999}}, {"TsValue": [-1.64, -1.94, -1.56, -1.34, -2.07, -1.59, -1.42, -1.62, -1.58, -1.52, -1.98, -1.59, -2.18, -2.85], "TsTime": [1060905600, 1067472000, 1068768000, 1071532800, 1074556800, 1077062400, 1080000000, 1082505600, 1084924800, 1087862400, 1090281600, 1092700800, 1095206400, 1216857600], "geometry": {"type": "Point", "coordinates": [-69.17580328813378, 18.993667371522488]}, "TsValue_norm": [-1.64, -1.94, -1.56, -1.34, -2.07, -1.59, -1.42, -1.62, -1.58, -1.52, -1.98, -1.59, -2.18, -2.85], "type": "Feature", "properties": {"Coordenada": 481496, "AquiferID": 2, "Coordena_1": 2100136, "HydroID": "6372110001", "LandElev": -9999}}, {"geometry": {"type": "Point", "coordinates": [-69.22088867015401, 18.9895882627357]}, "type": "Feature", "properties": {"Coordenada": 476750, "AquiferID": 2, "Coordena_1": 2099690, "HydroID": "6372110002", "LandElev": -9999}}, {"geometry": {"type": "Point", "coordinates": [-69.11635382548833, 18.989529851787417]}, "type": "Feature", "properties": {"Coordenada": 487753, "AquiferID": 2, "Coordena_1": 2099673, "HydroID": "6372120001", "LandElev": -9999}}, {"TsValue": [-1.23, -1.1, -1.04, -0.98, -1.25, -1.16, -1.2, -1.2, -1.09, -1.18, -1.27, -1.25], "TsTime": [1060905600, 1066953600, 1070409600, 1073606400, 1075852800, 1078876800, 1081123200, 1083801600, 1086739200, 1089244800, 1091577600, 1094256000], "geometry": {"type": "Point", "coordinates": [-69.04680765716368, 18.77792242185425]}, "TsValue_norm": [-1.23, -1.1, -1.04, -0.98, -1.25, -1.16, -1.2, -1.2, -1.09, -1.18, -1.27, -1.25], "type": "Feature", "properties": {"Coordenada": 495067, "AquiferID": 2, "Coordena_1": 2076256, "HydroID": "6372130001", "LandElev": -9999}}, {"geometry": {"type": "Point", "coordinates": [-69.05237258373037, 18.9759753501068]}, "type": "Feature", "properties": {"Coordenada": 494487, "AquiferID": 2, "Coordena_1": 2098170, "HydroID": "6372130002", "LandElev": -9999}}, {"geometry": {"type": "Point", "coordinates": [-69.08474349773473, 18.83501934439183]}, "type": "Feature", "properties": {"Coordenada": 491072, "AquiferID": 2, "Coordena_1": 2082575, "HydroID": "6372150001", "LandElev": -9999}}, {"geometry": {"type": "Point", "coordinates": [-69.08510413878311, 18.834919763850557]}, "type": "Feature", "properties": {"Coordenada": 491034, "AquiferID": 2, "Coordena_1": 2082564, "HydroID": "6372150002", "LandElev": -9999}}, {"TsValue": [-6.34, -4.93, -5.09, -4.81, -4.61, -8.91, -8.82, -4.58, -8.8, -8.72, -8.73, -9.72, -9.69, -5.85, -4.71, -2.44], "TsTime": [1060905600, 1066867200, 1068681600, 1070409600, 1073606400, 1075852800, 1078876800, 1081036800, 1083888000, 1086739200, 1089244800, 1091577600, 1094256000, 1183420800, 1215734400, 1282608000], "geometry": {"type": "Point", "coordinates": [-69.08370032302976, 18.836899686003502]}, "TsValue_norm": [-6.34, -4.93, -5.09, -4.81, -4.61, -8.91, -8.82, -4.58, -8.8, -8.72, -8.73, -9.72, -9.69, -5.85, -4.71, -2.44], "type": "Feature", "properties": {"Coordenada": 491182, "AquiferID": 2, "Coordena_1": 2082783, "HydroID": "6372150003", "LandElev": -9999}}, {"TsValue": [-9.75, -8.2, -7.48, -6.25, -6.19, -4.62, -4.27, -4.58, -4.45, -4.71, -4.48, -7.15, -7.09, -7.9, -6.68], "TsTime": [1060905600, 1066953600, 1068681600, 1070409600, 1073606400, 1075852800, 1078876800, 1081036800, 1083888000, 1086739200, 1089158400, 1091577600, 1094256000, 1183420800, 1282608000], "geometry": {"type": "Point", "coordinates": [-69.11209289921236, 18.868616541631724]}, "TsValue_norm": [-9.75, -8.2, -7.48, -6.25, -6.19, -4.62, -4.27, -4.58, -4.45, -4.71, -4.48, -7.15, -7.09, -7.9, -6.68], "type": "Feature", "properties": {"Coordenada": 488193, "AquiferID": 2, "Coordena_1": 2086294, "HydroID": "6372150004", "LandElev": -9999}}, {"TsValue": [-6.53, -5.12, -4.55, -3.6, -3.51, -6.65, -6.32, -6.0, -6.75, -6.69, -6.58, -7.63, -4.66], "TsTime": [1060905600, 1066867200, 1068681600, 1070409600, 1073865600, 1075766400, 1078876800, 1081036800, 1083628800, 1086739200, 1089158400, 1091577600, 1094169600], "geometry": {"type": "Point", "coordinates": [-69.1578045122507, 18.83730356386583]}, "TsValue_norm": [-6.53, -5.12, -4.55, -3.6, -3.51, -6.65, -6.32, -6.0, -6.75, -6.69, -6.58, -7.63, -4.66], "type": "Feature", "properties": {"Coordenada": 483375, "AquiferID": 2, "Coordena_1": 2082833, "HydroID": "6372150006", "LandElev": -9999}}, {"geometry": {"type": "Point", "coordinates": [-69.05295543951333, 18.835772189662777]}, "type": "Feature", "properties": {"Coordenada": 494421, "AquiferID": 2, "Coordena_1": 2082657, "HydroID": "6372160001", "LandElev": -9999}}, {"geometry": {"type": "Point", "coordinates": [-69.16847730680476, 18.79347880136543]}, "type": "Feature", "properties": {"Coordenada": 482246, "AquiferID": 2, "Coordena_1": 2077985, "HydroID": "637220002", "LandElev": -9999}}, {"geometry": {"type": "Point", "coordinates": [-69.21580067440854, 18.755561502334256]}, "type": "Feature", "properties": {"Coordenada": 477254, "AquiferID": 2, "Coordena_1": 2073795, "HydroID": "6372210002", "LandElev": -9999}}, {"geometry": {"type": "Point", "coordinates": [-69.19851972565922, 18.78420356183898]}, "type": "Feature", "properties": {"Coordenada": 479079, "AquiferID": 2, "Coordena_1": 2076962, "HydroID": "6372210003", "LandElev": -9999}}, {"geometry": {"type": "Point", "coordinates": [-69.1953381497922, 18.790036329358035]}, "type": "Feature", "properties": {"Coordenada": 479415, "AquiferID": 2, "Coordena_1": 2077607, "HydroID": "6372210004", "LandElev": -9999}}, {"geometry": {"type": "Point", "coordinates": [-69.19687934525676, 18.793414865324177]}, "type": "Feature", "properties": {"Coordenada": 479253, "AquiferID": 2, "Coordena_1": 2077981, "HydroID": "6372210005", "LandElev": -9999}}, {"TsValue": [-3.29, -6.08, -5.51, -4.57, -3.87, -4.45, -4.24, -5.75, -5.76, -4.47, -5.7, -6.72, -6.7, -4.87, -5.0, -3.5, -5.29, -21.6, -5.4, -4.85], "TsTime": [1060905600, 1066867200, 1068681600, 1070409600, 1073433600, 1075766400, 1078876800, 1081123200, 1083801600, 1086739200, 1089158400, 1091577600, 1094083200, 1154995200, 1183420800, 1196812800, 1215475200, 1279065600, 1319414400, 1326240000], "geometry": {"type": "Point", "coordinates": [-69.19738114039475, 18.792429210581716]}, "TsValue_norm": [-3.29, -6.08, -5.51, -4.57, -3.87, -4.45, -4.24, -5.75, -5.76, -4.47, -5.7, -6.72, -6.7, -4.87, -5.0, -3.5, -5.29, -21.6, -5.4, -4.85], "type": "Feature", "properties": {"Coordenada": 479200, "AquiferID": 2, "Coordena_1": 2077872, "HydroID": "6372210006", "LandElev": -9999}}, {"geometry": {"type": "Point", "coordinates": [-69.19260656295393, 18.79955601655689]}, "type": "Feature", "properties": {"Coordenada": 479704, "AquiferID": 2, "Coordena_1": 2078660, "HydroID": "6372210007", "LandElev": -9999}}, {"geometry": {"type": "Point", "coordinates": [-69.19254964447889, 18.799574150951603]}, "type": "Feature", "properties": {"Coordenada": 479710, "AquiferID": 2, "Coordena_1": 2078662, "HydroID": "6372210008", "LandElev": -9999}}, {"geometry": {"type": "Point", "coordinates": [-69.19280560257201, 18.799338902941386]}, "type": "Feature", "properties": {"Coordenada": 479683, "AquiferID": 2, "Coordena_1": 2078636, "HydroID": "6372210009", "LandElev": -9999}}, {"TsValue": [-3.61, -1.16, -2.52, -1.38, -1.36, -3.45, -3.56, -3.41, -3.46, -3.47, -3.46, -3.4, -3.44, -4.65, -6.68, -3.0, -5.78], "TsTime": [1060905600, 1066867200, 1068681600, 1070409600, 1073606400, 1075766400, 1078876800, 1081123200, 1083801600, 1086739200, 1089158400, 1091577600, 1094083200, 1154995200, 1183420800, 1196899200, 1215475200], "geometry": {"type": "Point", "coordinates": [-69.17642156169283, 18.804054784015538]}, "TsValue_norm": [-3.61, -1.16, -2.52, -1.38, -1.36, -3.45, -3.56, -3.41, -3.46, -3.47, -3.46, -3.4, -3.44, -4.65, -6.68, -3.0, -5.78], "type": "Feature", "properties": {"Coordenada": 481410, "AquiferID": 2, "Coordena_1": 2079156, "HydroID": "6372210010", "LandElev": -9999}}, {"geometry": {"type": "Point", "coordinates": [-69.24937371385546, 18.766600161248448]}, "type": "Feature", "properties": {"Coordenada": 473717, "AquiferID": 2, "Coordena_1": 2075021, "HydroID": "6372210011", "LandElev": -9999}}, {"TsValue": [-6.0, -5.43, -5.52, -5.71, -5.86, -6.15, -6.06, -5.0, -6.42, -6.58, -6.15, -6.6, -5.7, -7.27, -5.58, -4.82, -5.82], "TsTime": [1060905600, 1066867200, 1068595200, 1070409600, 1073606400, 1075680000, 1078704000, 1080864000, 1083715200, 1089072000, 1154995200, 1182211200, 1212537600, 1215475200, 1279065600, 1319414400, 1326153600], "geometry": {"type": "Point", "coordinates": [-69.2484747010557, 18.768201056549934]}, "TsValue_norm": [-6.0, -5.43, -5.52, -5.71, -5.86, -6.15, -6.06, -5.0, -6.42, -6.58, -6.15, -6.6, -5.7, -7.27, -5.58, -4.82, -5.82], "type": "Feature", "properties": {"Coordenada": 473812, "AquiferID": 2, "Coordena_1": 2075198, "HydroID": "6372210012", "LandElev": -9999}}, {"geometry": {"type": "Point", "coordinates": [-69.24281486404934, 18.77137173891789]}, "type": "Feature", "properties": {"Coordenada": 474409, "AquiferID": 2, "Coordena_1": 2075548, "HydroID": "6372210013", "LandElev": -9999}}, {"geometry": {"type": "Point", "coordinates": [-69.24016851835857, 18.77198973119978]}, "type": "Feature", "properties": {"Coordenada": 474688, "AquiferID": 2, "Coordena_1": 2075616, "HydroID": "6372210014", "LandElev": -9999}}, {"TsValue": [-7.2, -6.32, -5.64, -5.5, -6.02, -6.47, -6.17, -6.52, -6.58, -6.5, -6.71, -10.99, -10.94, -4.02], "TsTime": [1060905600, 1066867200, 1068595200, 1070409600, 1073606400, 1075680000, 1078704000, 1080950400, 1083715200, 1086825600, 1089072000, 1091577600, 1094083200, 1319414400], "geometry": {"type": "Point", "coordinates": [-69.23576211630697, 18.776053333014538]}, "TsValue_norm": [-7.2, -6.32, -5.64, -5.5, -6.02, -6.47, -6.17, -6.52, -6.58, -6.5, -6.71, -10.99, -10.94, -4.02], "type": "Feature", "properties": {"Coordenada": 475153, "AquiferID": 2, "Coordena_1": 2076065, "HydroID": "6372210015", "LandElev": -9999}}, {"TsValue": [-6.23, -7.3, -5.41, -5.36], "TsTime": [1182211200, 1215475200, 1279065600, 1326240000], "geometry": {"type": "Point", "coordinates": [-69.211905250231, 18.773867632196833]}, "TsValue_norm": [-6.23, -7.3, -5.41, -5.36], "type": "Feature", "properties": {"Coordenada": 477667, "AquiferID": 2, "Coordena_1": 2075820, "HydroID": "6372210016", "LandElev": -9999}}, {"geometry": {"type": "Point", "coordinates": [-69.17594746774739, 18.76789475477727]}, "type": "Feature", "properties": {"Coordenada": 481456, "AquiferID": 2, "Coordena_1": 2075155, "HydroID": "6372210017", "LandElev": -9999}}, {"TsValue": [-1.2, -0.63, -0.78, -1.04, -1.06, -2.14, -2.15, -2.09, -5.02, -5.08, -5.0, -2.14, -2.02, -4.12, -3.01, -2.75, -1.37, -1.8], "TsTime": [1060905600, 1066867200, 1068681600, 1070323200, 1073520000, 1075766400, 1078790400, 1081209600, 1083888000, 1089072000, 1091404800, 1094083200, 1182297600, 1196294400, 1212451200, 1216252800, 1279065600, 1319414400], "geometry": {"type": "Point", "coordinates": [-69.23765052262281, 18.789725185029567]}, "TsValue_norm": [-1.2, -0.63, -0.78, -1.04, -1.06, -2.14, -2.15, -2.09, -5.02, -5.08, -5.0, -2.14, -2.02, -4.12, -3.01, -2.75, -1.37, -1.8], "type": "Feature", "properties": {"Coordenada": 474956, "AquiferID": 2, "Coordena_1": 2077578, "HydroID": "6372210018", "LandElev": -9999}}, {"geometry": {"type": "Point", "coordinates": [-69.21725632609706, 18.803171201971548]}, "type": "Feature", "properties": {"Coordenada": 477107, "AquiferID": 2, "Coordena_1": 2079063, "HydroID": "6372210020", "LandElev": -9999}}, {"geometry": {"type": "Point", "coordinates": [-69.21862054368559, 18.80870075615032]}, "type": "Feature", "properties": {"Coordenada": 476964, "AquiferID": 2, "Coordena_1": 2079675, "HydroID": "6372210021", "LandElev": -9999}}, {"TsValue": [-6.25, -4.43, -5.23, -4.53, -4.35, -6.26, -6.38, -6.41, -5.4, -6.5, -6.43, -6.21, -6.24], "TsTime": [1060905600, 1066867200, 1068681600, 1070323200, 1073520000, 1075766400, 1078790400, 1081209600, 1083888000, 1086739200, 1089072000, 1091404800, 1094083200], "geometry": {"type": "Point", "coordinates": [-69.24224242683796, 18.815621658199774]}, "TsValue_norm": [-6.25, -4.43, -5.23, -4.53, -4.35, -6.26, -6.38, -6.41, -5.4, -6.5, -6.43, -6.21, -6.24], "type": "Feature", "properties": {"Coordenada": 474476, "AquiferID": 2, "Coordena_1": 2080444, "HydroID": "6372210022", "LandElev": -9999}}, {"TsValue": [-4.94, -6.0, -5.52, -5.17, -4.6, -5.58], "TsTime": [1196294400, 1212451200, 1216252800, 1279065600, 1319414400, 1326153600], "geometry": {"type": "Point", "coordinates": [-69.2378566135401, 18.814841012907753]}, "TsValue_norm": [-4.94, -6.0, -5.52, -5.17, -4.6, -5.58], "type": "Feature", "properties": {"Coordenada": 474938, "AquiferID": 2, "Coordena_1": 2080357, "HydroID": "6372210023", "LandElev": -9999}}, {"geometry": {"type": "Point", "coordinates": [-69.23810321824168, 18.81473224468391]}, "type": "Feature", "properties": {"Coordenada": 474912, "AquiferID": 2, "Coordena_1": 2080345, "HydroID": "6372210024", "LandElev": -9999}}, {"geometry": {"type": "Point", "coordinates": [-69.2386928633572, 18.815599120272584]}, "type": "Feature", "properties": {"Coordenada": 474850, "AquiferID": 2, "Coordena_1": 2080441, "HydroID": "6372210025", "LandElev": -9999}}, {"geometry": {"type": "Point", "coordinates": [-69.23882734099016, 18.81673771120112]}, "type": "Feature", "properties": {"Coordenada": 474836, "AquiferID": 2, "Coordena_1": 2080567, "HydroID": "6372210026", "LandElev": -9999}}, {"geometry": {"type": "Point", "coordinates": [-69.23886691215988, 18.81787642343542]}, "type": "Feature", "properties": {"Coordenada": 474832, "AquiferID": 2, "Coordena_1": 2080693, "HydroID": "6372210027", "LandElev": -9999}}, {"geometry": {"type": "Point", "coordinates": [-69.23934186321392, 18.818165024215652]}, "type": "Feature", "properties": {"Coordenada": 474782, "AquiferID": 2, "Coordena_1": 2080725, "HydroID": "6372210028", "LandElev": -9999}}, {"geometry": {"type": "Point", "coordinates": [-69.2376506882644, 18.81688381878663]}, "type": "Feature", "properties": {"Coordenada": 474960, "AquiferID": 2, "Coordena_1": 2080583, "HydroID": "6372210029", "LandElev": -9999}}, {"geometry": {"type": "Point", "coordinates": [-69.23774626931692, 18.81736270047517]}, "type": "Feature", "properties": {"Coordenada": 474950, "AquiferID": 2, "Coordena_1": 2080636, "HydroID": "6372210030", "LandElev": -9999}}, {"geometry": {"type": "Point", "coordinates": [-69.20097398025108, 18.765329885644622]}, "type": "Feature", "properties": {"Coordenada": 478818, "AquiferID": 2, "Coordena_1": 2074874, "HydroID": "6372210032", "LandElev": -9999}}, {"geometry": {"type": "Point", "coordinates": [-69.18411589758043, 18.749657479306233]}, "type": "Feature", "properties": {"Coordenada": 480593, "AquiferID": 2, "Coordena_1": 2073138, "HydroID": "63722133", "LandElev": -9999}}, {"geometry": {"type": "Point", "coordinates": [-69.16164468566826, 18.803245722164306]}, "type": "Feature", "properties": {"Coordenada": 482967, "AquiferID": 2, "Coordena_1": 2079065, "HydroID": "6372220001", "LandElev": -9999}}, {"TsValue": [-6.22, -7.1, -7.22, -7.14, -8.35, -8.63, -8.36, -8.33, -8.39, -8.26, -8.21, -8.38, -8.12, -8.33, -7.93], "TsTime": [1060905600, 1068681600, 1070409600, 1073606400, 1075766400, 1078876800, 1081123200, 1083801600, 1086739200, 1089158400, 1091577600, 1094083200, 1183420800, 1215475200, 1282608000], "geometry": {"type": "Point", "coordinates": [-69.16865270377549, 18.788553010634857]}, "TsValue_norm": [-6.22, -7.1, -7.22, -7.14, -8.35, -8.63, -8.36, -8.33, -8.39, -8.26, -8.21, -8.38, -8.12, -8.33, -7.93], "type": "Feature", "properties": {"Coordenada": 482227, "AquiferID": 2, "Coordena_1": 2077440, "HydroID": "6372220003", "LandElev": -9999}}, {"geometry": {"type": "Point", "coordinates": [-69.11254043982689, 18.785070475929857]}, "type": "Feature", "properties": {"Coordenada": 488140, "AquiferID": 2, "Coordena_1": 2077050, "HydroID": "6372220004", "LandElev": -9999}}, {"geometry": {"type": "Point", "coordinates": [-69.11356679096718, 18.787356438270837]}, "type": "Feature", "properties": {"Coordenada": 488032, "AquiferID": 2, "Coordena_1": 2077303, "HydroID": "6372220005", "LandElev": -9999}}, {"geometry": {"type": "Point", "coordinates": [-69.12247411182157, 18.7962892653189]}, "type": "Feature", "properties": {"Coordenada": 487094, "AquiferID": 2, "Coordena_1": 2078292, "HydroID": "6372220006", "LandElev": -9999}}, {"geometry": {"type": "Point", "coordinates": [-69.12206117163363, 18.80267930579646]}, "type": "Feature", "properties": {"Coordenada": 487138, "AquiferID": 2, "Coordena_1": 2078999, "HydroID": "6372220007", "LandElev": -9999}}, {"geometry": {"type": "Point", "coordinates": [-69.16051332034091, 18.821096432735764]}, "type": "Feature", "properties": {"Coordenada": 483088, "AquiferID": 2, "Coordena_1": 2081040, "HydroID": "6372220009", "LandElev": -9999}}, {"TsValue": [-7.46, -4.43, -4.11, -4.05, -5.97, -5.31, -5.83, -5.83, -5.87, -5.78, -4.7, -4.61], "TsTime": [1060905600, 1066867200, 1070409600, 1073865600, 1075766400, 1078876800, 1081036800, 1083801600, 1086739200, 1089158400, 1091577600, 1094083200], "geometry": {"type": "Point", "coordinates": [-69.16347129088193, 18.817740827834175]}, "TsValue_norm": [-7.46, -4.43, -4.11, -4.05, -5.97, -5.31, -5.83, -5.83, -5.87, -5.78, -4.7, -4.61], "type": "Feature", "properties": {"Coordenada": 482776, "AquiferID": 2, "Coordena_1": 2080669, "HydroID": "6372220010", "LandElev": -9999}}, {"geometry": {"type": "Point", "coordinates": [-69.10941815562114, 18.79917141525495]}, "type": "Feature", "properties": {"Coordenada": 488470, "AquiferID": 2, "Coordena_1": 2078610, "HydroID": "6372220011", "LandElev": -9999}}, {"geometry": {"type": "Point", "coordinates": [-69.11035283286556, 18.806337891365278]}, "type": "Feature", "properties": {"Coordenada": 488372, "AquiferID": 2, "Coordena_1": 2079403, "HydroID": "6372220012", "LandElev": -9999}}, {"TsValue": [-7.5, -6.43, -6.34, -6.11, -6.1, -6.33, -6.12, -6.35, -7.37, -5.8, -6.63, -6.7, -9.72], "TsTime": [1060905600, 1066953600, 1068681600, 1070409600, 1073865600, 1075852800, 1078876800, 1081036800, 1083888000, 1089158400, 1091577600, 1094169600, 1282608000], "geometry": {"type": "Point", "coordinates": [-69.10956551029501, 18.806907740461416]}, "TsValue_norm": [-7.5, -6.43, -6.34, -6.11, -6.1, -6.33, -6.12, -6.35, -7.37, -5.8, -6.63, -6.7, -9.72], "type": "Feature", "properties": {"Coordenada": 488455, "AquiferID": 2, "Coordena_1": 2079466, "HydroID": "6372220013", "LandElev": -9999}}, {"geometry": {"type": "Point", "coordinates": [-69.1042122987398, 18.821199654717784]}, "type": "Feature", "properties": {"Coordenada": 489020, "AquiferID": 2, "Coordena_1": 2081047, "HydroID": "6372220014", "LandElev": -9999}}, {"geometry": {"type": "Point", "coordinates": [-69.09964792006522, 18.822621091440627]}, "type": "Feature", "properties": {"Coordenada": 489501, "AquiferID": 2, "Coordena_1": 2081204, "HydroID": "6372220015", "LandElev": -9999}}, {"TsValue": [-2.59, -2.1, -2.15, -2.1, -2.14, -2.02, -2.07, -2.3, -2.0, -2.35, -2.3, -2.28, -3.45, -2.64, -2.09], "TsTime": [1060905600, 1066953600, 1068681600, 1070409600, 1073865600, 1075852800, 1078876800, 1081036800, 1083888000, 1089158400, 1091577600, 1094169600, 1183420800, 1215734400, 1282608000], "geometry": {"type": "Point", "coordinates": [-69.09993928910707, 18.81778568595617]}, "TsValue_norm": [-2.59, -2.1, -2.15, -2.1, -2.14, -2.02, -2.07, -2.3, -2.0, -2.35, -2.3, -2.28, -3.45, -2.64, -2.09], "type": "Feature", "properties": {"Coordenada": 489470, "AquiferID": 2, "Coordena_1": 2080669, "HydroID": "6372220016", "LandElev": -9999}}, {"geometry": {"type": "Point", "coordinates": [-69.08948527975157, 18.827172281918894]}, "type": "Feature", "properties": {"Coordenada": 490572, "AquiferID": 2, "Coordena_1": 2081707, "HydroID": "6372220018", "LandElev": -9999}}, {"geometry": {"type": "Point", "coordinates": [-69.08996208786725, 18.813533934412025]}, "type": "Feature", "properties": {"Coordenada": 490521, "AquiferID": 2, "Coordena_1": 2080198, "HydroID": "6372220019", "LandElev": -9999}}, {"geometry": {"type": "Point", "coordinates": [-69.08545970727184, 18.82478817885706]}, "type": "Feature", "properties": {"Coordenada": 490996, "AquiferID": 2, "Coordena_1": 2081443, "HydroID": "6372220020", "LandElev": -9999}}, {"geometry": {"type": "Point", "coordinates": [-69.09420313941642, 18.828281612734898]}, "type": "Feature", "properties": {"Coordenada": 490075, "AquiferID": 2, "Coordena_1": 2081830, "HydroID": "6372222001", "LandElev": -9999}}, {"geometry": {"type": "Point", "coordinates": [-69.04681718577413, 18.778067025851826]}, "type": "Feature", "properties": {"Coordenada": 495066, "AquiferID": 2, "Coordena_1": 2076272, "HydroID": "6372230002", "LandElev": -9999}}, {"geometry": {"type": "Point", "coordinates": [-69.00470675293987, 18.79115066536582]}, "type": "Feature", "properties": {"Coordenada": 499504, "AquiferID": 2, "Coordena_1": 2077719, "HydroID": "6372230003", "LandElev": -9999}}, {"geometry": {"type": "Point", "coordinates": [-69.02169375290954, 18.798461113410003]}, "type": "Feature", "properties": {"Coordenada": 497714, "AquiferID": 2, "Coordena_1": 2078528, "HydroID": "6372230004", "LandElev": -9999}}, {"geometry": {"type": "Point", "coordinates": [-69.00971853228161, 18.814929126533528]}, "type": "Feature", "properties": {"Coordenada": 498976, "AquiferID": 2, "Coordena_1": 2080350, "HydroID": "6372230006", "LandElev": -9999}}, {"geometry": {"type": "Point", "coordinates": [-69.06079124690176, 18.82320719046702]}, "type": "Feature", "properties": {"Coordenada": 493595, "AquiferID": 2, "Coordena_1": 2081267, "HydroID": "6372230007", "LandElev": -9999}}, {"geometry": {"type": "Point", "coordinates": [-69.04081248779974, 18.824242948496817]}, "type": "Feature", "properties": {"Coordenada": 495700, "AquiferID": 2, "Coordena_1": 2081381, "HydroID": "6372230008", "LandElev": -9999}}, {"TsValue": [-12.13, -12.02, -11.9, -11.33, -11.27, -11.03, -10.69, -10.74, -10.55, -10.64, -10.53, -10.5], "TsTime": [1060905600, 1067299200, 1068854400, 1070409600, 1073606400, 1078963200, 1081123200, 1083801600, 1086739200, 1089244800, 1091664000, 1094256000], "geometry": {"type": "Point", "coordinates": [-69.04005120604637, 18.815883093981263]}, "TsValue_norm": [-12.13, -12.02, -11.9, -11.33, -11.27, -11.03, -10.69, -10.74, -10.55, -10.64, -10.53, -10.5], "type": "Feature", "properties": {"Coordenada": 495780, "AquiferID": 2, "Coordena_1": 2080456, "HydroID": "6372230009", "LandElev": -9999}}, {"TsValue": [-7.26, -11.42, -10.98, -10.48, -10.57, -11.25, -11.93, -11.89, -12.03, -12.15, -12.27, -11.29, -12.2, -9.68, -12.14, -11.95, -8.08, -8.06], "TsTime": [1060905600, 1066780800, 1068595200, 1070236800, 1073433600, 1075766400, 1078790400, 1080864000, 1083628800, 1086652800, 1088985600, 1091404800, 1093996800, 1182211200, 1212451200, 1216252800, 1319414400, 1326153600], "geometry": {"type": "Point", "coordinates": [-69.2415440505102, 18.711750540888694]}, "TsValue_norm": [-7.26, -11.42, -10.98, -10.48, -10.57, -11.25, -11.93, -11.89, -12.03, -12.15, -12.27, -11.29, -12.2, -9.68, -12.14, -11.95, -8.08, -8.06], "type": "Feature", "properties": {"Coordenada": 474534, "AquiferID": 2, "Coordena_1": 2068951, "HydroID": "6372240001", "LandElev": -9999}}, {"geometry": {"type": "Point", "coordinates": [-69.2342434281412, 18.699974371637545]}, "type": "Feature", "properties": {"Coordenada": 475302, "AquiferID": 2, "Coordena_1": 2067647, "HydroID": "6372240002", "LandElev": -9999}}, {"geometry": {"type": "Point", "coordinates": [-69.25024705710857, 18.715381394757912]}, "type": "Feature", "properties": {"Coordenada": 473617, "AquiferID": 2, "Coordena_1": 2069354, "HydroID": "6372240003", "LandElev": -9999}}, {"geometry": {"type": "Point", "coordinates": [-69.2485252054676, 18.71842041799464]}, "type": "Feature", "properties": {"Coordenada": 473799, "AquiferID": 2, "Coordena_1": 2069690, "HydroID": "6372240004", "LandElev": -9999}}, {"geometry": {"type": "Point", "coordinates": [-69.21180950690787, 18.69706372486528]}, "type": "Feature", "properties": {"Coordenada": 477667, "AquiferID": 2, "Coordena_1": 2067322, "HydroID": "6372240005", "LandElev": -9999}}, {"TsValue": [-10.53, -10.04, -7.63, -7.89, -7.24, -7.46, -7.8, -8.67, -8.65, -14.6, -14.93, -10.47, -11.6, -9.32, -8.78], "TsTime": [1060905600, 1068595200, 1070409600, 1073520000, 1075766400, 1078790400, 1081036800, 1083715200, 1089072000, 1091491200, 1094083200, 1154995200, 1182211200, 1196812800, 1215475200], "geometry": {"type": "Point", "coordinates": [-69.19495153206395, 18.69296070463597]}, "TsValue_norm": [-10.53, -10.04, -7.63, -7.89, -7.24, -7.46, -7.8, -8.67, -8.65, -14.6, -14.93, -10.47, -11.6, -9.32, -8.78], "type": "Feature", "properties": {"Coordenada": 479444, "AquiferID": 2, "Coordena_1": 2066866, "HydroID": "6372240006", "LandElev": -9999}}, {"geometry": {"type": "Point", "coordinates": [-69.19833349042241, 18.68970350050682]}, "type": "Feature", "properties": {"Coordenada": 479087, "AquiferID": 2, "Coordena_1": 2066506, "HydroID": "6372240007", "LandElev": -9999}}, {"geometry": {"type": "Point", "coordinates": [-69.19763883228804, 18.68767973397085]}, "type": "Feature", "properties": {"Coordenada": 479160, "AquiferID": 2, "Coordena_1": 2066282, "HydroID": "6372240008", "LandElev": -9999}}, {"geometry": {"type": "Point", "coordinates": [-69.19785520251747, 18.686170168938556]}, "type": "Feature", "properties": {"Coordenada": 479137, "AquiferID": 2, "Coordena_1": 2066115, "HydroID": "6372240009", "LandElev": -9999}}, {"geometry": {"type": "Point", "coordinates": [-69.19874626185235, 18.685834823279926]}, "type": "Feature", "properties": {"Coordenada": 479043, "AquiferID": 2, "Coordena_1": 2066078, "HydroID": "6372240010", "LandElev": -9999}}, {"TsValue": [-4.3, -0.8, -5.77, -1.05, -1.09, -4.39, -4.08, -4.02, -3.87, -4.05, -0.9, -1.03], "TsTime": [1060905600, 1066953600, 1068595200, 1070409600, 1073520000, 1078790400, 1080950400, 1083715200, 1086739200, 1089072000, 1091491200, 1094083200], "geometry": {"type": "Point", "coordinates": [-69.17432787402889, 18.70595949088143]}, "TsValue_norm": [-4.3, -0.8, -5.77, -1.05, -1.09, -4.39, -4.08, -4.02, -3.87, -4.05, -0.9, -1.03], "type": "Feature", "properties": {"Coordenada": 481620, "AquiferID": 2, "Coordena_1": 2068302, "HydroID": "6372240015", "LandElev": -9999}}, {"TsValue": [-1.55, -2.87, -3.25, -2.45, -3.05, -3.07, -3.22, -3.18, -3.15, -3.67, -3.19, -3.26, -3.69], "TsTime": [1060905600, 1066780800, 1068595200, 1070236800, 1073433600, 1075680000, 1078704000, 1080864000, 1083628800, 1086652800, 1088985600, 1091404800, 1093996800], "geometry": {"type": "Point", "coordinates": [-69.23381230980021, 18.738232332316468]}, "TsValue_norm": [-1.55, -2.87, -3.25, -2.45, -3.05, -3.07, -3.22, -3.18, -3.15, -3.67, -3.19, -3.26, -3.69], "type": "Feature", "properties": {"Coordenada": 475353, "AquiferID": 2, "Coordena_1": 2071880, "HydroID": "6372240016", "LandElev": -9999}}, {"geometry": {"type": "Point", "coordinates": [-69.23459611111835, 18.735646517904847]}, "type": "Feature", "properties": {"Coordenada": 475270, "AquiferID": 2, "Coordena_1": 2071594, "HydroID": "6372240017", "LandElev": -9999}}, {"geometry": {"type": "Point", "coordinates": [-69.23161895956578, 18.73677092206885]}, "type": "Feature", "properties": {"Coordenada": 475584, "AquiferID": 2, "Coordena_1": 2071718, "HydroID": "6372240018", "LandElev": -9999}}, {"TsValue": [-3.85], "TsTime": [1154995200], "geometry": {"type": "Point", "coordinates": [-69.23531700258997, 18.73560042383276]}, "TsValue_norm": [-3.85], "type": "Feature", "properties": {"Coordenada": 475194, "AquiferID": 2, "Coordena_1": 2071589, "HydroID": "6372240019", "LandElev": -9999}}, {"geometry": {"type": "Point", "coordinates": [-69.2369684390531, 18.736194841045716]}, "type": "Feature", "properties": {"Coordenada": 475020, "AquiferID": 2, "Coordena_1": 2071655, "HydroID": "6372240020", "LandElev": -9999}}, {"geometry": {"type": "Point", "coordinates": [-69.24158264412691, 18.7389183826133]}, "type": "Feature", "properties": {"Coordenada": 474534, "AquiferID": 2, "Coordena_1": 2071957, "HydroID": "6372240021", "LandElev": -9999}}, {"geometry": {"type": "Point", "coordinates": [-69.17575685397789, 18.739579221869025]}, "type": "Feature", "properties": {"Coordenada": 481473, "AquiferID": 2, "Coordena_1": 2072022, "HydroID": "6372240022", "LandElev": -9999}}, {"TsValue": [-31.64, -22.82, -20.18, -21.28, -21.97, -27.85, -28.41, -27.89, -27.61, -27.86, -22.04, -23.13, -14.72, -11.23, -8.9, -9.25, -8.9, -21.94], "TsTime": [1060905600, 1066867200, 1068595200, 1070409600, 1073433600, 1075766400, 1078790400, 1080950400, 1083715200, 1089072000, 1091491200, 1094083200, 1154995200, 1182211200, 1196812800, 1215475200, 1282521600, 1319414400], "geometry": {"type": "Point", "coordinates": [-69.17151213133278, 18.73536245598097]}, "TsValue_norm": [-31.64, -22.82, -20.18, -21.28, -21.97, -27.85, -28.41, -27.89, -27.61, -27.86, -22.04, -23.13, -14.72, -11.23, -8.9, -9.25, -8.9, -21.94], "type": "Feature", "properties": {"Coordenada": 481920, "AquiferID": 2, "Coordena_1": 2071555, "HydroID": "6372240023", "LandElev": -9999}}, {"geometry": {"type": "Point", "coordinates": [-69.17554652644007, 18.73800682368931]}, "type": "Feature", "properties": {"Coordenada": 481495, "AquiferID": 2, "Coordena_1": 2071848, "HydroID": "6372240024", "LandElev": -9999}}, {"geometry": {"type": "Point", "coordinates": [-69.23263224131739, 18.70774898272375]}, "type": "Feature", "properties": {"Coordenada": 475473, "AquiferID": 2, "Coordena_1": 2068507, "HydroID": "6372240025", "LandElev": -9999}}, {"geometry": {"type": "Point", "coordinates": [-69.1666311756997, 18.68179900602147]}, "type": "Feature", "properties": {"Coordenada": 482429, "AquiferID": 2, "Coordena_1": 2065628, "HydroID": "6372250001", "LandElev": -9999}}, {"TsValue": [-4.28, -5.27, -5.14, -5.19, -3.37, -3.69, -3.8, -1.17, -1.12], "TsTime": [1070409600, 1075766400, 1078790400, 1080950400, 1083715200, 1086825600, 1089072000, 1094083200, 1154995200], "geometry": {"type": "Point", "coordinates": [-69.15710724474192, 18.68914604614973]}, "TsValue_norm": [-4.28, -5.27, -5.14, -5.19, -3.37, -3.69, -3.8, -1.17, -1.12], "type": "Feature", "properties": {"Coordenada": 483434, "AquiferID": 2, "Coordena_1": 2066440, "HydroID": "6372250003", "LandElev": -9999}}, {"geometry": {"type": "Point", "coordinates": [-69.16451517876104, 18.70999024128131]}, "type": "Feature", "properties": {"Coordenada": 482655, "AquiferID": 2, "Coordena_1": 2068747, "HydroID": "6372250005", "LandElev": -9999}}, {"geometry": {"type": "Point", "coordinates": [-69.1677789793312, 18.72063403099558]}, "type": "Feature", "properties": {"Coordenada": 482312, "AquiferID": 2, "Coordena_1": 2069925, "HydroID": "6372250006", "LandElev": -9999}}, {"geometry": {"type": "Point", "coordinates": [-69.16715106079448, 18.709066039784286]}, "type": "Feature", "properties": {"Coordenada": 482377, "AquiferID": 2, "Coordena_1": 2068645, "HydroID": "6372250007", "LandElev": -9999}}, {"geometry": {"type": "Point", "coordinates": [-69.17026509194022, 18.693111266543653]}, "type": "Feature", "properties": {"Coordenada": 482047, "AquiferID": 2, "Coordena_1": 2066880, "HydroID": "6372250008", "LandElev": -9999}}, {"geometry": {"type": "Point", "coordinates": [-69.16920580322153, 18.69604052092182]}, "type": "Feature", "properties": {"Coordenada": 482159, "AquiferID": 2, "Coordena_1": 2067204, "HydroID": "6372250009", "LandElev": -9999}}, {"geometry": {"type": "Point", "coordinates": [-69.16214560067365, 18.70174970282787]}, "type": "Feature", "properties": {"Coordenada": 482904, "AquiferID": 2, "Coordena_1": 2067835, "HydroID": "6372250010", "LandElev": -9999}}, {"geometry": {"type": "Point", "coordinates": [-69.16771558042548, 18.704429072747157]}, "type": "Feature", "properties": {"Coordenada": 482317, "AquiferID": 2, "Coordena_1": 2068132, "HydroID": "6372250011", "LandElev": -9999}}, {"geometry": {"type": "Point", "coordinates": [-69.16461314724712, 18.673955830487664]}, "type": "Feature", "properties": {"Coordenada": 482641, "AquiferID": 2, "Coordena_1": 2064760, "HydroID": "6372250012", "LandElev": -9999}}, {"geometry": {"type": "Point", "coordinates": [-69.14605241571084, 18.670699437393527]}, "type": "Feature", "properties": {"Coordenada": 484598, "AquiferID": 2, "Coordena_1": 2064398, "HydroID": "6372250013", "LandElev": -9999}}, {"TsValue": [-4.42, -4.06, -3.83, -3.77, -3.98, -4.11], "TsTime": [1067299200, 1068854400, 1070496000, 1073865600, 1075852800, 1078099200], "geometry": {"type": "Point", "coordinates": [-69.01735798468209, 18.809035882045908]}, "TsValue_norm": [-4.42, -4.06, -3.83, -3.77, -3.98, -4.11], "type": "Feature", "properties": {"Coordenada": 498171, "AquiferID": 2, "Coordena_1": 2079698, "HydroID": "637230005", "LandElev": -9999}}, {"geometry": {"type": "Point", "coordinates": [-69.43424032881519, 18.831143653920634]}, "type": "Feature", "properties": {"Coordenada": 454250, "AquiferID": 2, "Coordena_1": 2082200, "HydroID": "6372310001", "LandElev": -9999}}, {"geometry": {"type": "Point", "coordinates": [-69.40223762065479, 18.760278495252653]}, "type": "Feature", "properties": {"Coordenada": 457604, "AquiferID": 2, "Coordena_1": 2074351, "HydroID": "6372320001", "LandElev": -9999}}, {"geometry": {"type": "Point", "coordinates": [-69.41100181579527, 18.771095675192857]}, "type": "Feature", "properties": {"Coordenada": 456683, "AquiferID": 2, "Coordena_1": 2075550, "HydroID": "6372320002", "LandElev": -9999}}, {"geometry": {"type": "Point", "coordinates": [-69.40767465850469, 18.772413431310003]}, "type": "Feature", "properties": {"Coordenada": 457034, "AquiferID": 2, "Coordena_1": 2075695, "HydroID": "6372320003", "LandElev": -9999}}, {"TsValue": [-11.91, -11.45, -11.12, -10.93, -10.78, -11.54, -11.92, -12.7, -12.63, -13.27, -13.3, -13.07, -12.86, -12.83, -11.03, -11.9, -12.04, -9.05], "TsTime": [1060905600, 1067385600, 1068681600, 1070323200, 1073520000, 1075766400, 1078790400, 1080864000, 1083628800, 1086652800, 1088985600, 1091491200, 1093996800, 1182124800, 1196985600, 1212537600, 1216339200, 1319414400], "geometry": {"type": "Point", "coordinates": [-69.4085412747673, 18.769799636697744]}, "TsValue_norm": [-11.91, -11.45, -11.12, -10.93, -10.78, -11.54, -11.92, -12.7, -12.63, -13.27, -13.3, -13.07, -12.86, -12.83, -11.03, -11.9, -12.04, -9.05], "type": "Feature", "properties": {"Coordenada": 456942, "AquiferID": 2, "Coordena_1": 2075406, "HydroID": "6372320004", "LandElev": -9999}}, {"TsValue": [-6.27], "TsTime": [1212537600], "geometry": {"type": "Point", "coordinates": [-69.38606556394542, 18.799599616678595]}, "TsValue_norm": [-6.27], "type": "Feature", "properties": {"Coordenada": 459318, "AquiferID": 2, "Coordena_1": 2078698, "HydroID": "6372320005", "LandElev": -9999}}, {"TsValue": [-23.95, -17.12, -18.18, -18.83, -18.6, -45.65, -45.67, -43.0, -42.5, -43.0, -34.18, -46.0, -26.08, -18.87, -17.4, -21.2, -24.46], "TsTime": [1060905600, 1067385600, 1068681600, 1070323200, 1073520000, 1075766400, 1078790400, 1080864000, 1083628800, 1088985600, 1091491200, 1093996800, 1182124800, 1196985600, 1212537600, 1279065600, 1319414400], "geometry": {"type": "Point", "coordinates": [-69.38696750890368, 18.80393585199707]}, "TsValue_norm": [-23.95, -17.12, -18.18, -18.83, -18.6, -45.65, -45.67, -43.0, -42.5, -43.0, -34.18, -46.0, -26.08, -18.87, -17.4, -21.2, -24.46], "type": "Feature", "properties": {"Coordenada": 459224, "AquiferID": 2, "Coordena_1": 2079178, "HydroID": "6372320006", "LandElev": -9999}}, {"TsValue": [-11.95, -9.77, -9.18, -8.89, -8.57, -11.27, -11.78, -11.3, -11.27, -13.88, -12.35, -12.01, -11.9, -10.02, -10.4, -10.3, -9.74, -9.36], "TsTime": [1060905600, 1067385600, 1068681600, 1070323200, 1073520000, 1075766400, 1078790400, 1080950400, 1083628800, 1086652800, 1089072000, 1093996800, 1182124800, 1196985600, 1212537600, 1216339200, 1279065600, 1319414400], "geometry": {"type": "Point", "coordinates": [-69.36568522091326, 18.810052114667645]}, "TsValue_norm": [-11.95, -9.77, -9.18, -8.89, -8.57, -11.27, -11.78, -11.3, -11.27, -13.88, -12.35, -12.01, -11.9, -10.02, -10.4, -10.3, -9.74, -9.36], "type": "Feature", "properties": {"Coordenada": 461468, "AquiferID": 2, "Coordena_1": 2079850, "HydroID": "6372320007", "LandElev": -9999}}, {"TsValue": [-3.41, -1.5, -1.84, -1.94, -1.98, -4.92, -4.98, -4.89, -4.83, -5.88, -5.92, -5.87, -5.32, -2.94, -2.42, -4.47, -2.26, -2.19], "TsTime": [1060905600, 1067385600, 1068681600, 1070323200, 1073520000, 1075766400, 1078790400, 1080950400, 1083715200, 1086652800, 1089072000, 1091404800, 1093996800, 1182297600, 1196985600, 1216339200, 1279065600, 1319414400], "geometry": {"type": "Point", "coordinates": [-69.35048654828732, 18.798639501471925]}, "TsValue_norm": [-3.41, -1.5, -1.84, -1.94, -1.98, -4.92, -4.98, -4.89, -4.83, -5.88, -5.92, -5.87, -5.32, -2.94, -2.42, -4.47, -2.26, -2.19], "type": "Feature", "properties": {"Coordenada": 463067, "AquiferID": 2, "Coordena_1": 2078584, "HydroID": "6372320008", "LandElev": -9999}}, {"TsValue": [-7.0, -4.2, -4.84, -4.89, -6.41, -7.83, -7.92, -7.8, -9.52, -8.36, -8.62, -8.76, -5.9], "TsTime": [1060905600, 1067385600, 1068681600, 1070323200, 1073520000, 1075766400, 1078790400, 1080950400, 1083715200, 1089072000, 1091404800, 1093996800, 1182124800], "geometry": {"type": "Point", "coordinates": [-69.33399626728168, 18.7808201403223]}, "TsValue_norm": [-7.0, -4.2, -4.84, -4.89, -6.41, -7.83, -7.92, -7.8, -9.52, -8.36, -8.62, -8.76, -5.9], "type": "Feature", "properties": {"Coordenada": 464801, "AquiferID": 2, "Coordena_1": 2076609, "HydroID": "6372320009", "LandElev": -9999}}, {"geometry": {"type": "Point", "coordinates": [-69.31831705008385, 18.788873062024155]}, "type": "Feature", "properties": {"Coordenada": 466455, "AquiferID": 2, "Coordena_1": 2077497, "HydroID": "6372330001", "LandElev": -9999}}, {"geometry": {"type": "Point", "coordinates": [-69.32330906411542, 18.789244074106186]}, "type": "Feature", "properties": {"Coordenada": 465929, "AquiferID": 2, "Coordena_1": 2077539, "HydroID": "6372330002", "LandElev": -9999}}, {"geometry": {"type": "Point", "coordinates": [-69.27524332523814, 18.764087500999523]}, "type": "Feature", "properties": {"Coordenada": 470990, "AquiferID": 2, "Coordena_1": 2074747, "HydroID": "6372330003", "LandElev": -9999}}, {"geometry": {"type": "Point", "coordinates": [-69.24993209192523, 18.765641404156646]}, "type": "Feature", "properties": {"Coordenada": 473658, "AquiferID": 2, "Coordena_1": 2074915, "HydroID": "6372330004", "LandElev": -9999}}, {"geometry": {"type": "Point", "coordinates": [-69.24895680080799, 18.76698030631785]}, "type": "Feature", "properties": {"Coordenada": 473761, "AquiferID": 2, "Coordena_1": 2075063, "HydroID": "6372330005", "LandElev": -9999}}, {"geometry": {"type": "Point", "coordinates": [-69.26462515327408, 18.775418195727983]}, "type": "Feature", "properties": {"Coordenada": 472111, "AquiferID": 2, "Coordena_1": 2075999, "HydroID": "6372330006", "LandElev": -9999}}, {"geometry": {"type": "Point", "coordinates": [-69.26427509526988, 18.776069414598112]}, "type": "Feature", "properties": {"Coordenada": 472148, "AquiferID": 2, "Coordena_1": 2076071, "HydroID": "6372330007", "LandElev": -9999}}, {"TsValue": [-2.94, -4.9], "TsTime": [1182124800, 1212537600], "geometry": {"type": "Point", "coordinates": [-69.26512840794256, 18.775652465960768]}, "TsValue_norm": [-2.94, -4.9], "type": "Feature", "properties": {"Coordenada": 472058, "AquiferID": 2, "Coordena_1": 2076025, "HydroID": "6372330008", "LandElev": -9999}}, {"TsValue": [-7.4, -6.3, -5.86, -5.79, -6.81, -6.37, -6.79, -6.73, -6.77, -7.86, -8.05, -6.88, -5.7, -7.31, -7.14, -6.28, -6.81], "TsTime": [1060905600, 1066780800, 1068595200, 1073433600, 1075680000, 1078704000, 1080864000, 1083628800, 1088985600, 1091404800, 1093996800, 1182124800, 1196899200, 1212537600, 1216252800, 1279065600, 1319414400], "geometry": {"type": "Point", "coordinates": [-69.26580506341176, 18.77754944808055]}, "TsValue_norm": [-7.4, -6.3, -5.86, -5.79, -6.81, -6.37, -6.79, -6.73, -6.77, -7.86, -8.05, -6.88, -5.7, -7.31, -7.14, -6.28, -6.81], "type": "Feature", "properties": {"Coordenada": 471987, "AquiferID": 2, "Coordena_1": 2076235, "HydroID": "6372330009", "LandElev": -9999}}, {"geometry": {"type": "Point", "coordinates": [-69.26827513429348, 18.779470974396574]}, "type": "Feature", "properties": {"Coordenada": 471727, "AquiferID": 2, "Coordena_1": 2076448, "HydroID": "6372330010", "LandElev": -9999}}, {"geometry": {"type": "Point", "coordinates": [-69.27256521738948, 18.786116597691688]}, "type": "Feature", "properties": {"Coordenada": 471276, "AquiferID": 2, "Coordena_1": 2077184, "HydroID": "6372330011", "LandElev": -9999}}, {"geometry": {"type": "Point", "coordinates": [-69.27154615465936, 18.78378632592553]}, "type": "Feature", "properties": {"Coordenada": 471383, "AquiferID": 2, "Coordena_1": 2076926, "HydroID": "6372330012", "LandElev": -9999}}, {"geometry": {"type": "Point", "coordinates": [-69.28059246494436, 18.803005396430986]}, "type": "Feature", "properties": {"Coordenada": 470433, "AquiferID": 2, "Coordena_1": 2079054, "HydroID": "6372330013", "LandElev": -9999}}, {"geometry": {"type": "Point", "coordinates": [-69.27703349488777, 18.808668369265234]}, "type": "Feature", "properties": {"Coordenada": 470809, "AquiferID": 2, "Coordena_1": 2079680, "HydroID": "6372330014", "LandElev": -9999}}, {"geometry": {"type": "Point", "coordinates": [-69.27688448936074, 18.810403845478348]}, "type": "Feature", "properties": {"Coordenada": 470825, "AquiferID": 2, "Coordena_1": 2079872, "HydroID": "6372330015", "LandElev": -9999}}, {"geometry": {"type": "Point", "coordinates": [-69.26513576252829, 18.816720248984705]}, "type": "Feature", "properties": {"Coordenada": 472064, "AquiferID": 2, "Coordena_1": 2080569, "HydroID": "6372330017", "LandElev": -9999}}, {"geometry": {"type": "Point", "coordinates": [-69.28059308786632, 18.809105902310773]}, "type": "Feature", "properties": {"Coordenada": 470434, "AquiferID": 2, "Coordena_1": 2079729, "HydroID": "6372330018", "LandElev": -9999}}, {"TsValue": [-10.19, -9.61, -6.98, -5.95, -8.56, -8.28, -8.59, -8.57, -8.66, -10.98, -10.63], "TsTime": [1060905600, 1066780800, 1068595200, 1073433600, 1075680000, 1078704000, 1080864000, 1083628800, 1088985600, 1091404800, 1093996800], "geometry": {"type": "Point", "coordinates": [-69.28820119198728, 18.80725963751306]}, "TsValue_norm": [-10.19, -9.61, -6.98, -5.95, -8.56, -8.28, -8.59, -8.57, -8.66, -10.98, -10.63], "type": "Feature", "properties": {"Coordenada": 469632, "AquiferID": 2, "Coordena_1": 2079526, "HydroID": "6372330019", "LandElev": -9999}}, {"TsValue": [-7.98, -5.62, -5.46, -6.12, -4.4, -7.69, -7.71, -7.7, -7.31, -10.01, -10.31, -6.28, -8.16, -7.3, -6.72, -4.9, -7.21], "TsTime": [1060905600, 1066780800, 1068595200, 1073433600, 1075680000, 1078704000, 1080864000, 1083628800, 1088985600, 1091404800, 1093996800, 1182124800, 1196899200, 1212537600, 1216252800, 1279065600, 1319414400], "geometry": {"type": "Point", "coordinates": [-69.27954904521323, 18.797548134413645]}, "TsValue_norm": [-7.98, -5.62, -5.46, -6.12, -4.4, -7.69, -7.71, -7.7, -7.31, -10.01, -10.31, -6.28, -8.16, -7.3, -6.72, -4.9, -7.21], "type": "Feature", "properties": {"Coordenada": 470542, "AquiferID": 2, "Coordena_1": 2078450, "HydroID": "6372330020", "LandElev": -9999}}, {"geometry": {"type": "Point", "coordinates": [-69.44494133636454, 18.731514140550164]}, "type": "Feature", "properties": {"Coordenada": 453095, "AquiferID": 2, "Coordena_1": 2071179, "HydroID": "6372340004", "LandElev": -9999}}, {"geometry": {"type": "Point", "coordinates": [-69.40952060306815, 18.715561949528624]}, "type": "Feature", "properties": {"Coordenada": 456825, "AquiferID": 2, "Coordena_1": 2069405, "HydroID": "6372350001", "LandElev": -9999}}, {"geometry": {"type": "Point", "coordinates": [-69.32988727602242, 18.73669586100878]}, "type": "Feature", "properties": {"Coordenada": 465225, "AquiferID": 2, "Coordena_1": 2071726, "HydroID": "6372350003", "LandElev": -9999}}, {"geometry": {"type": "Point", "coordinates": [-69.38266211326169, 18.725361462953025]}, "type": "Feature", "properties": {"Coordenada": 459659, "AquiferID": 2, "Coordena_1": 2070483, "HydroID": "6372350004", "LandElev": -9999}}, {"geometry": {"type": "Point", "coordinates": [-69.34087206303904, 18.72236027546267]}, "type": "Feature", "properties": {"Coordenada": 464064, "AquiferID": 2, "Coordena_1": 2070142, "HydroID": "6372350005", "LandElev": -9999}}, {"geometry": {"type": "Point", "coordinates": [-69.33507695353232, 18.669580608106898]}, "type": "Feature", "properties": {"Coordenada": 464664, "AquiferID": 2, "Coordena_1": 2064301, "HydroID": "6372350006", "LandElev": -9999}}, {"geometry": {"type": "Point", "coordinates": [-69.33416764506022, 18.670097387701613]}, "type": "Feature", "properties": {"Coordenada": 464760, "AquiferID": 2, "Coordena_1": 2064358, "HydroID": "6372350007", "LandElev": -9999}}, {"geometry": {"type": "Point", "coordinates": [-69.33554857531946, 18.682766026417667]}, "type": "Feature", "properties": {"Coordenada": 464617, "AquiferID": 2, "Coordena_1": 2065760, "HydroID": "6372350008", "LandElev": -9999}}, {"geometry": {"type": "Point", "coordinates": [-69.34215408736367, 18.680621163992786]}, "type": "Feature", "properties": {"Coordenada": 463920, "AquiferID": 2, "Coordena_1": 2065524, "HydroID": "6372350009", "LandElev": -9999}}, {"geometry": {"type": "Point", "coordinates": [-69.34462225838314, 18.667809985828036]}, "type": "Feature", "properties": {"Coordenada": 463657, "AquiferID": 2, "Coordena_1": 2064107, "HydroID": "6372350010", "LandElev": -9999}}, {"geometry": {"type": "Point", "coordinates": [-69.3611479178088, 18.733872601673518]}, "type": "Feature", "properties": {"Coordenada": 461929, "AquiferID": 2, "Coordena_1": 2071420, "HydroID": "6372350011", "LandElev": -9999}}, {"TsValue": [-9.0, -7.3, -7.46, -7.33, -8.37, -8.41, -6.18, -10.14, -9.98, -10.02, -10.41, -10.36, -5.32, -5.31, -8.02], "TsTime": [1060905600, 1067385600, 1068681600, 1073433600, 1075766400, 1078790400, 1080950400, 1083801600, 1086739200, 1088985600, 1091491200, 1093996800, 1196985600, 1282521600, 1319414400], "geometry": {"type": "Point", "coordinates": [-69.35809629125973, 18.73524317088569]}, "TsValue_norm": [-9.0, -7.3, -7.46, -7.33, -8.37, -8.41, -6.18, -10.14, -9.98, -10.02, -10.41, -10.36, -5.32, -5.31, -8.02], "type": "Feature", "properties": {"Coordenada": 462251, "AquiferID": 2, "Coordena_1": 2071571, "HydroID": "6372350012", "LandElev": -9999}}, {"geometry": {"type": "Point", "coordinates": [-69.36289646550019, 18.730886746739316]}, "type": "Feature", "properties": {"Coordenada": 461744, "AquiferID": 2, "Coordena_1": 2071090, "HydroID": "6372350013", "LandElev": -9999}}, {"TsValue": [-10.87], "TsTime": [1278460800], "geometry": {"type": "Point", "coordinates": [-69.27658803040688, 18.71005720883426]}, "TsValue_norm": [-10.87], "type": "Feature", "properties": {"Coordenada": 470839, "AquiferID": 2, "Coordena_1": 2068769, "HydroID": "6372360001", "LandElev": -9999}}, {"geometry": {"type": "Point", "coordinates": [-69.27643990079088, 18.71812825328555]}, "type": "Feature", "properties": {"Coordenada": 470856, "AquiferID": 2, "Coordena_1": 2069662, "HydroID": "6372360002", "LandElev": -9999}}, {"geometry": {"type": "Point", "coordinates": [-69.26183400717119, 18.737517397267315]}, "type": "Feature", "properties": {"Coordenada": 472399, "AquiferID": 2, "Coordena_1": 2071805, "HydroID": "6372360003", "LandElev": -9999}}, {"TsValue": [-7.37, -2.58, -1.63, -1.77, -3.38, -3.46, -3.46, -3.24, -3.92, -4.07, -4.1, -5.2, -4.03, -4.03, -3.04], "TsTime": [1066953600, 1068681600, 1070323200, 1073520000, 1075766400, 1078790400, 1081036800, 1083715200, 1089158400, 1091577600, 1094169600, 1182297600, 1196985600, 1215475200, 1319414400], "geometry": {"type": "Point", "coordinates": [-69.28141223852418, 18.70216899381091]}, "TsValue_norm": [-7.37, -2.58, -1.63, -1.77, -3.38, -3.46, -3.46, -3.24, -3.92, -4.07, -4.1, -5.2, -4.03, -4.03, -3.04], "type": "Feature", "properties": {"Coordenada": 470329, "AquiferID": 2, "Coordena_1": 2067897, "HydroID": "6372360004", "LandElev": -9999}}, {"TsValue": [-12.81], "TsTime": [1216252800], "geometry": {"type": "Point", "coordinates": [-69.2826947695764, 18.70345948234226]}, "TsValue_norm": [-12.81], "type": "Feature", "properties": {"Coordenada": 470194, "AquiferID": 2, "Coordena_1": 2068040, "HydroID": "6372360005", "LandElev": -9999}}, {"TsValue": [-14.42, -13.53, -13.59, -8.86, -8.93, -8.83, -10.76, -8.91, -9.41, -9.37, -11.78, -6.86, -13.27, -7.53, -7.87], "TsTime": [1060905600, 1067385600, 1068681600, 1075766400, 1078790400, 1081036800, 1083715200, 1089158400, 1091577600, 1094169600, 1182211200, 1196899200, 1215475200, 1279065600, 1319414400], "geometry": {"type": "Point", "coordinates": [-69.32295620123051, 18.673479098533107]}, "TsValue_norm": [-14.42, -13.53, -13.59, -8.86, -8.93, -8.83, -10.76, -8.91, -9.41, -9.37, -11.78, -6.86, -13.27, -7.53, -7.87], "type": "Feature", "properties": {"Coordenada": 465943, "AquiferID": 2, "Coordena_1": 2064730, "HydroID": "6372360006", "LandElev": -9999}}, {"TsValue": [-5.86, -5.05, -5.12, -5.02, -5.65, -6.01, -6.7, -6.05, -6.1, -6.08, -5.89, -5.87, -7.03, -6.9, -6.62, -6.09, -5.89], "TsTime": [1060905600, 1067385600, 1068681600, 1070323200, 1073433600, 1075680000, 1078790400, 1081209600, 1083801600, 1088985600, 1091491200, 1094169600, 1182297600, 1196899200, 1215475200, 1279065600, 1319414400], "geometry": {"type": "Point", "coordinates": [-69.3203505237884, 18.719965311417297]}, "TsValue_norm": [-5.86, -5.05, -5.12, -5.02, -5.65, -6.01, -6.7, -6.05, -6.1, -6.08, -5.89, -5.87, -7.03, -6.9, -6.62, -6.09, -5.89], "type": "Feature", "properties": {"Coordenada": 466227, "AquiferID": 2, "Coordena_1": 2069873, "HydroID": "6372360007", "LandElev": -9999}}, {"geometry": {"type": "Point", "coordinates": [-69.24896422054874, 18.707294185136323]}, "type": "Feature", "properties": {"Coordenada": 473751, "AquiferID": 2, "Coordena_1": 2068459, "HydroID": "6372360008", "LandElev": -9999}}, {"geometry": {"type": "Point", "coordinates": [-69.30135603244662, 18.674337458894257]}, "type": "Feature", "properties": {"Coordenada": 468221, "AquiferID": 2, "Coordena_1": 2064821, "HydroID": "6372360009", "LandElev": -9999}}, {"geometry": {"type": "Point", "coordinates": [-69.26650161415131, 18.683211176811806]}, "type": "Feature", "properties": {"Coordenada": 471898, "AquiferID": 2, "Coordena_1": 2065797, "HydroID": "6372360010", "LandElev": -9999}}, {"geometry": {"type": "Point", "coordinates": [-69.26693449118325, 18.687123977713952]}, "type": "Feature", "properties": {"Coordenada": 471853, "AquiferID": 2, "Coordena_1": 2066230, "HydroID": "6372360011", "LandElev": -9999}}, {"geometry": {"type": "Point", "coordinates": [-69.26719997277416, 18.68708744821628]}, "type": "Feature", "properties": {"Coordenada": 471825, "AquiferID": 2, "Coordena_1": 2066226, "HydroID": "6372360012", "LandElev": -9999}}, {"TsValue": [-3.0, -1.95, -2.16, -2.6, -2.81, -4.27, -4.85, -4.59, -4.62, -3.69, -4.02, -3.76, -5.05, -4.46, -2.7, -3.25], "TsTime": [1060905600, 1066867200, 1068595200, 1070236800, 1073433600, 1075680000, 1078704000, 1080864000, 1083628800, 1086652800, 1088985600, 1091404800, 1093996800, 1212451200, 1319414400, 1326153600], "geometry": {"type": "Point", "coordinates": [-69.26622318556788, 18.68709787452]}, "TsValue_norm": [-3.0, -1.95, -2.16, -2.6, -2.81, -4.27, -4.85, -4.59, -4.62, -3.69, -4.02, -3.76, -5.05, -4.46, -2.7, -3.25], "type": "Feature", "properties": {"Coordenada": 471928, "AquiferID": 2, "Coordena_1": 2066227, "HydroID": "6372360014", "LandElev": -9999}}, {"geometry": {"type": "Point", "coordinates": [-69.26761430944993, 18.68521601014736]}, "type": "Feature", "properties": {"Coordenada": 471781, "AquiferID": 2, "Coordena_1": 2066019, "HydroID": "6372360015", "LandElev": -9999}}, {"geometry": {"type": "Point", "coordinates": [-69.26740516411708, 18.684890943445584]}, "type": "Feature", "properties": {"Coordenada": 471803, "AquiferID": 2, "Coordena_1": 2065983, "HydroID": "6372360016", "LandElev": -9999}}, {"geometry": {"type": "Point", "coordinates": [-69.26822536899613, 18.681807844426228]}, "type": "Feature", "properties": {"Coordenada": 471716, "AquiferID": 2, "Coordena_1": 2065642, "HydroID": "6372360017", "LandElev": -9999}}, {"geometry": {"type": "Point", "coordinates": [-69.26265010732236, 18.694685715964834]}, "type": "Feature", "properties": {"Coordenada": 472306, "AquiferID": 2, "Coordena_1": 2067066, "HydroID": "6372360020", "LandElev": -9999}}, {"geometry": {"type": "Point", "coordinates": [-69.26228124973747, 18.695345999203546]}, "type": "Feature", "properties": {"Coordenada": 472345, "AquiferID": 2, "Coordena_1": 2067139, "HydroID": "6372360021", "LandElev": -9999}}, {"TsValue": [-6.1, -7.65, -7.08, -7.71, -8.03, -8.17, -8.19, -9.53, -9.27, -9.66, -9.57, -9.7, -12.83, -9.34, -9.11, -7.42, -11.12, -11.22], "TsTime": [1060905600, 1068595200, 1070236800, 1073433600, 1075680000, 1078704000, 1080864000, 1083628800, 1086652800, 1088985600, 1091404800, 1093996800, 1182211200, 1212451200, 1216252800, 1278460800, 1319414400, 1326153600], "geometry": {"type": "Point", "coordinates": [-69.26141743161851, 18.69484108235016]}, "TsValue_norm": [-6.1, -7.65, -7.08, -7.71, -8.03, -8.17, -8.19, -9.53, -9.27, -9.66, -9.57, -9.7, -12.83, -9.34, -9.11, -7.42, -11.12, -11.22], "type": "Feature", "properties": {"Coordenada": 472436, "AquiferID": 2, "Coordena_1": 2067083, "HydroID": "6372360022", "LandElev": -9999}}, {"geometry": {"type": "Point", "coordinates": [-69.26083297003643, 18.69715559981771]}, "type": "Feature", "properties": {"Coordenada": 472498, "AquiferID": 2, "Coordena_1": 2067339, "HydroID": "6372360023", "LandElev": -9999}}, {"geometry": {"type": "Point", "coordinates": [-69.25911991410004, 18.699498791560345]}, "type": "Feature", "properties": {"Coordenada": 472679, "AquiferID": 2, "Coordena_1": 2067598, "HydroID": "6372360024", "LandElev": -9999}}, {"geometry": {"type": "Point", "coordinates": [-69.25873237990608, 18.7003669653102]}, "type": "Feature", "properties": {"Coordenada": 472720, "AquiferID": 2, "Coordena_1": 2067694, "HydroID": "6372360025", "LandElev": -9999}}, {"geometry": {"type": "Point", "coordinates": [-69.25829820174059, 18.7017503628775]}, "type": "Feature", "properties": {"Coordenada": 472766, "AquiferID": 2, "Coordena_1": 2067847, "HydroID": "6372360026", "LandElev": -9999}}, {"geometry": {"type": "Point", "coordinates": [-69.25821548801245, 18.703494791636732]}, "type": "Feature", "properties": {"Coordenada": 472775, "AquiferID": 2, "Coordena_1": 2068040, "HydroID": "6372360027", "LandElev": -9999}}, {"TsValue": [-9.93, -2.31, -2.45, -2.45, -2.63, -4.32, -4.83, -5.0, -4.24, -4.88, -5.62, -6.08, -10.4, -6.52, -4.96], "TsTime": [1060905600, 1066780800, 1068595200, 1070236800, 1073433600, 1075680000, 1078704000, 1080864000, 1083628800, 1086652800, 1089244800, 1093996800, 1193961600, 1319414400, 1326153600], "geometry": {"type": "Point", "coordinates": [-69.24897197861772, 18.719079590879595]}, "TsValue_norm": [-9.93, -2.31, -2.45, -2.45, -2.63, -4.32, -4.83, -5.0, -4.24, -4.88, -5.62, -6.08, -10.4, -6.52, -4.96], "type": "Feature", "properties": {"Coordenada": 473752, "AquiferID": 2, "Coordena_1": 2069763, "HydroID": "6372360028", "LandElev": -9999}}, {"geometry": {"type": "Point", "coordinates": [-69.41728696988837, 18.976036851262542]}, "type": "Feature", "properties": {"Coordenada": 456074, "AquiferID": 2, "Coordena_1": 2098228, "HydroID": "6372410005", "LandElev": -9999}}, {"geometry": {"type": "Point", "coordinates": [-69.37617345967577, 18.92562292841412]}, "type": "Feature", "properties": {"Coordenada": 460390, "AquiferID": 2, "Coordena_1": 2092640, "HydroID": "6372420001", "LandElev": -9999}}, {"geometry": {"type": "Point", "coordinates": [-69.37403149985525, 18.978713998777362]}, "type": "Feature", "properties": {"Coordenada": 460628, "AquiferID": 2, "Coordena_1": 2098514, "HydroID": "6372420002", "LandElev": -9999}}, {"TsValue": [-12.59, -15.54, -14.55, -11.9, -11.43, -16.13, -12.06, -12.23, -12.59, -12.35, -10.21, -11.14, -5.86], "TsTime": [1060905600, 1067472000, 1068768000, 1071532800, 1073865600, 1077062400, 1080000000, 1082505600, 1084924800, 1090368000, 1092700800, 1095120000, 1216857600], "geometry": {"type": "Point", "coordinates": [-69.41203431943794, 18.976301662068487]}, "TsValue_norm": [-12.59, -15.54, -14.55, -11.9, -11.43, -16.13, -12.06, -12.23, -12.59, -12.35, -10.21, -11.14, -5.86], "type": "Feature", "properties": {"Coordenada": 456627, "AquiferID": 2, "Coordena_1": 2098256, "HydroID": "6372420003", "LandElev": -9999}}, {"geometry": {"type": "Point", "coordinates": [-69.41203431943794, 18.976301662068487]}, "type": "Feature", "properties": {"Coordenada": 456627, "AquiferID": 2, "Coordena_1": 2098256, "HydroID": "6372420004", "LandElev": -9999}}, {"geometry": {"type": "Point", "coordinates": [-69.26605804289005, 18.817785394561362]}, "type": "Feature", "properties": {"Coordenada": 471967, "AquiferID": 2, "Coordena_1": 2080687, "HydroID": "6373330016", "LandElev": -9999}}, {"geometry": {"type": "Point", "coordinates": [-69.42453532742518, 19.039752697000722]}, "type": "Feature", "properties": {"Coordenada": 455328, "AquiferID": 2, "Coordena_1": 2105280, "HydroID": "6373340001", "LandElev": -9999}}, {"TsValue": [-0.81, -1.02, -2.35, -2.29, -1.6, -1.61, -1.54, -1.54, -1.82, -1.71, -1.51, -2.21], "TsTime": [1060905600, 1068768000, 1071532800, 1074556800, 1077062400, 1080000000, 1082505600, 1084924800, 1090368000, 1092700800, 1095120000, 1216857600], "geometry": {"type": "Point", "coordinates": [-69.3876678539709, 19.04608770188557]}, "TsValue_norm": [-0.81, -1.02, -2.35, -2.29, -1.6, -1.61, -1.54, -1.54, -1.82, -1.71, -1.51, -2.21], "type": "Feature", "properties": {"Coordenada": 459209, "AquiferID": 2, "Coordena_1": 2105972, "HydroID": "6373350001", "LandElev": -9999}}, {"TsValue": [-1.7, -1.23, -1.23, -1.29, -1.09, -1.03, -1.31, -1.09, -1.06], "TsTime": [1071532800, 1074556800, 1080000000, 1082505600, 1084924800, 1087862400, 1090368000, 1092700800, 1095120000], "geometry": {"type": "Point", "coordinates": [-69.38732673078016, 19.04652221672114]}, "TsValue_norm": [-1.7, -1.23, -1.23, -1.29, -1.09, -1.03, -1.31, -1.09, -1.06], "type": "Feature", "properties": {"Coordenada": 459245, "AquiferID": 2, "Coordena_1": 2106020, "HydroID": "6373350002", "LandElev": -9999}}, {"geometry": {"type": "Point", "coordinates": [-69.38680273336202, 19.045962991659408]}, "type": "Feature", "properties": {"Coordenada": 459300, "AquiferID": 2, "Coordena_1": 2105958, "HydroID": "6373350003", "LandElev": -9999}}, {"geometry": {"type": "Point", "coordinates": [-69.40753191933746, 19.050581728541655]}, "type": "Feature", "properties": {"Coordenada": 457120, "AquiferID": 2, "Coordena_1": 2106474, "HydroID": "6373350004", "LandElev": -9999}}, {"geometry": {"type": "Point", "coordinates": [-69.25816230945738, 19.010028298213005]}, "type": "Feature", "properties": {"Coordenada": 472830, "AquiferID": 2, "Coordena_1": 2101957, "HydroID": "6373360001", "LandElev": -9999}}, {"geometry": {"type": "Point", "coordinates": [-69.31089602789841, 19.0301641862889]}, "type": "Feature", "properties": {"Coordenada": 467284, "AquiferID": 2, "Coordena_1": 2104194, "HydroID": "6373360002", "LandElev": -9999}}, {"geometry": {"type": "Point", "coordinates": [-69.38445100749823, 19.064711617626983]}, "type": "Feature", "properties": {"Coordenada": 459552, "AquiferID": 2, "Coordena_1": 2108032, "HydroID": "6373450004", "LandElev": -9999}}, {"TsValue": [-2.81, -1.54, -1.0, -1.4, -1.3, -1.4], "TsTime": [1060905600, 1067472000, 1068854400, 1071100800, 1074556800, 1076976000], "geometry": {"type": "Point", "coordinates": [-69.38930014749788, 19.061384700849416]}, "TsValue_norm": [-2.81, -1.54, -1.0, -1.4, -1.3, -1.4], "type": "Feature", "properties": {"Coordenada": 459041, "AquiferID": 2, "Coordena_1": 2107665, "HydroID": "6373450005", "LandElev": -9999}}, {"geometry": {"type": "Point", "coordinates": [-68.70226814137064, 18.60804094660217]}, "type": "Feature", "properties": {"Coordenada": 531409, "AquiferID": 2, "Coordena_1": 2057485, "HydroID": "6471110001", "LandElev": -9999}}, {"TsValue": [-10.02, -6.51, -5.26, -4.98, -5.01, -5.45, -5.51, -6.25, -6.07, -5.39, -5.05, -5.86, -5.88, -5.32, -5.9, -12.18, -5.91, -5.0, -4.31], "TsTime": [1060905600, 1067299200, 1068854400, 1070496000, 1073606400, 1075852800, 1078963200, 1081209600, 1083888000, 1086912000, 1089244800, 1091664000, 1094169600, 1154995200, 1212624000, 1216339200, 1216684800, 1278547200, 1319414400], "geometry": {"type": "Point", "coordinates": [-68.89280136638064, 18.66554686625083]}, "TsValue_norm": [-10.02, -6.51, -5.26, -4.98, -5.01, -5.45, -5.51, -6.25, -6.07, -5.39, -5.05, -5.86, -5.88, -5.32, -5.9, -12.18, -5.91, -5.0, -4.31], "type": "Feature", "properties": {"Coordenada": 511305, "AquiferID": 2, "Coordena_1": 2063825, "HydroID": "6471420001", "LandElev": -9999}}, {"geometry": {"type": "Point", "coordinates": [-68.89202329512132, 18.666359840262796]}, "type": "Feature", "properties": {"Coordenada": 511387, "AquiferID": 2, "Coordena_1": 2063915, "HydroID": "6471420002", "LandElev": -9999}}, {"TsValue": [-14.17, -13.0, -12.16, -11.59, -11.43, -12.15, -12.79, -12.03, -12.31, -13.17, -12.07, -11.32, -11.38, -12.05], "TsTime": [1060905600, 1067299200, 1068854400, 1070496000, 1073606400, 1075852800, 1078963200, 1081123200, 1083801600, 1086912000, 1089244800, 1091664000, 1094256000, 1216339200], "geometry": {"type": "Point", "coordinates": [-68.85288975504426, 18.65479175164076]}, "TsValue_norm": [-14.17, -13.0, -12.16, -11.59, -11.43, -12.15, -12.79, -12.03, -12.31, -13.17, -12.07, -11.32, -11.38, -12.05], "type": "Feature", "properties": {"Coordenada": 515515, "AquiferID": 2, "Coordena_1": 2062638, "HydroID": "6471420003", "LandElev": -9999}}, {"geometry": {"type": "Point", "coordinates": [-68.87501476536694, 18.649348814082646]}, "type": "Feature", "properties": {"Coordenada": 513182, "AquiferID": 2, "Coordena_1": 2062034, "HydroID": "6471420004", "LandElev": -9999}}, {"geometry": {"type": "Point", "coordinates": [-68.83548348491072, 18.66225173428913]}, "type": "Feature", "properties": {"Coordenada": 517350, "AquiferID": 2, "Coordena_1": 2063465, "HydroID": "6471420006", "LandElev": -9999}}, {"geometry": {"type": "Point", "coordinates": [-68.82840863591822, 18.663375152690392]}, "type": "Feature", "properties": {"Coordenada": 518096, "AquiferID": 2, "Coordena_1": 2063590, "HydroID": "6471430001", "LandElev": -9999}}, {"geometry": {"type": "Point", "coordinates": [-68.66819935101795, 18.81766196206899]}, "type": "Feature", "properties": {"Coordenada": 534960, "AquiferID": 2, "Coordena_1": 2080685, "HydroID": "6472220001", "LandElev": -9999}}, {"geometry": {"type": "Point", "coordinates": [-68.66247070559045, 18.79672929709462]}, "type": "Feature", "properties": {"Coordenada": 535568, "AquiferID": 2, "Coordena_1": 2078370, "HydroID": "6472220002", "LandElev": -9999}}, {"geometry": {"type": "Point", "coordinates": [-68.64490879705261, 18.699856787299602]}, "type": "Feature", "properties": {"Coordenada": 537440, "AquiferID": 2, "Coordena_1": 2067655, "HydroID": "6472250001", "LandElev": -9999}}, {"geometry": {"type": "Point", "coordinates": [-68.99535885355142, 18.82103891716076]}, "type": "Feature", "properties": {"Coordenada": 500489, "AquiferID": 2, "Coordena_1": 2081026, "HydroID": "6472310001", "LandElev": -9999}}, {"geometry": {"type": "Point", "coordinates": [-68.95678610965659, 18.750258236335274]}, "type": "Feature", "properties": {"Coordenada": 504555, "AquiferID": 2, "Coordena_1": 2073195, "HydroID": "6472310002", "LandElev": -9999}}, {"geometry": {"type": "Point", "coordinates": [-68.94221927083373, 18.76228377477275]}, "type": "Feature", "properties": {"Coordenada": 506090, "AquiferID": 2, "Coordena_1": 2074526, "HydroID": "6472310003", "LandElev": -9999}}, {"geometry": {"type": "Point", "coordinates": [-68.91104339164144, 18.76031935486966]}, "type": "Feature", "properties": {"Coordenada": 509376, "AquiferID": 2, "Coordena_1": 2074310, "HydroID": "6472320001", "LandElev": -9999}}, {"geometry": {"type": "Point", "coordinates": [-68.86994855598311, 18.789867254761617]}, "type": "Feature", "properties": {"Coordenada": 513705, "AquiferID": 2, "Coordena_1": 2077582, "HydroID": "6472320002", "LandElev": -9999}}, {"geometry": {"type": "Point", "coordinates": [-68.87234708571528, 18.818048952167835]}, "type": "Feature", "properties": {"Coordenada": 513450, "AquiferID": 2, "Coordena_1": 2080700, "HydroID": "6472320004", "LandElev": -9999}}, {"geometry": {"type": "Point", "coordinates": [-68.98829316719801, 18.74605118504161]}, "type": "Feature", "properties": {"Coordenada": 501234, "AquiferID": 2, "Coordena_1": 2072729, "HydroID": "6472340001", "LandElev": -9999}}, {"geometry": {"type": "Point", "coordinates": [-68.99083559014397, 18.747271447582932]}, "type": "Feature", "properties": {"Coordenada": 500966, "AquiferID": 2, "Coordena_1": 2072864, "HydroID": "6472340002", "LandElev": -9999}}, {"TsValue": [-15.14, -14.22, -12.73, -8.69, -8.88, -11.05, -13.5, -14.15, -14.89, -12.57, -12.62, -12.74, -11.24, -6.57, -11.33, -2.72, -5.98, -5.62], "TsTime": [1060905600, 1067299200, 1068854400, 1070496000, 1073606400, 1078963200, 1081123200, 1083801600, 1089244800, 1091664000, 1094169600, 1154995200, 1183420800, 1196294400, 1212624000, 1279065600, 1319414400, 1326240000], "geometry": {"type": "Point", "coordinates": [-68.97385385519303, 18.747694628110562]}, "TsValue_norm": [-15.14, -14.22, -12.73, -8.69, -8.88, -11.05, -13.5, -14.15, -14.89, -12.57, -12.62, -12.74, -11.24, -6.57, -11.33, -2.72, -5.98, -5.62], "type": "Feature", "properties": {"Coordenada": 502756, "AquiferID": 2, "Coordena_1": 2072911, "HydroID": "6472340003", "LandElev": -9999}}, {"geometry": {"type": "Point", "coordinates": [-68.9221339708577, 18.678585070280462]}, "type": "Feature", "properties": {"Coordenada": 508211, "AquiferID": 2, "Coordena_1": 2065266, "HydroID": "6472340004", "LandElev": -9999}}, {"geometry": {"type": "Point", "coordinates": [-68.92178324432427, 18.67825955680384]}, "type": "Feature", "properties": {"Coordenada": 508248, "AquiferID": 2, "Coordena_1": 2065230, "HydroID": "6472340005", "LandElev": -9999}}, {"TsValue": [-8.83, -7.16, -4.76, -4.66, -4.92, -8.13, -8.41, -8.26, -8.1, -8.05, -3.79, -8.67, -8.71, -7.54, -7.82, -7.78], "TsTime": [1060905600, 1067299200, 1068854400, 1070496000, 1073606400, 1075852800, 1078963200, 1081209600, 1083888000, 1086912000, 1089244800, 1091664000, 1094169600, 1154995200, 1212624000, 1216339200], "geometry": {"type": "Point", "coordinates": [-68.91816163726727, 18.676296768773085]}, "TsValue_norm": [-8.83, -7.16, -4.76, -4.66, -4.92, -8.13, -8.41, -8.26, -8.1, -8.05, -3.79, -8.67, -8.71, -7.54, -7.82, -7.78], "type": "Feature", "properties": {"Coordenada": 508630, "AquiferID": 2, "Coordena_1": 2065013, "HydroID": "6472340006", "LandElev": -9999}}, {"geometry": {"type": "Point", "coordinates": [-68.91634126463897, 18.675554851049863]}, "type": "Feature", "properties": {"Coordenada": 508822, "AquiferID": 2, "Coordena_1": 2064931, "HydroID": "6472340007", "LandElev": -9999}}, {"geometry": {"type": "Point", "coordinates": [-68.93766613377545, 18.6818897374176]}, "type": "Feature", "properties": {"Coordenada": 506573, "AquiferID": 2, "Coordena_1": 2065631, "HydroID": "6472340008", "LandElev": -9999}}, {"geometry": {"type": "Point", "coordinates": [-68.88709866318268, 18.742763843454863]}, "type": "Feature", "properties": {"Coordenada": 511901, "AquiferID": 2, "Coordena_1": 2072369, "HydroID": "6472350001", "LandElev": -9999}}, {"geometry": {"type": "Point", "coordinates": [-68.88473788006779, 18.74069272041792]}, "type": "Feature", "properties": {"Coordenada": 512150, "AquiferID": 2, "Coordena_1": 2072140, "HydroID": "6472350002", "LandElev": -9999}}, {"geometry": {"type": "Point", "coordinates": [-68.91395195564434, 18.674767465817933]}, "type": "Feature", "properties": {"Coordenada": 509074, "AquiferID": 2, "Coordena_1": 2064844, "HydroID": "6472350003", "LandElev": -9999}}, {"geometry": {"type": "Point", "coordinates": [-68.90555226588326, 18.670840939250187]}, "type": "Feature", "properties": {"Coordenada": 509960, "AquiferID": 2, "Coordena_1": 2064410, "HydroID": "6472350004", "LandElev": -9999}}, {"geometry": {"type": "Point", "coordinates": [-68.90557121126015, 18.67087710075759]}, "type": "Feature", "properties": {"Coordenada": 509958, "AquiferID": 2, "Coordena_1": 2064414, "HydroID": "6472350005", "LandElev": -9999}}, {"geometry": {"type": "Point", "coordinates": [-68.88817907962675, 18.672196134029846]}, "type": "Feature", "properties": {"Coordenada": 511792, "AquiferID": 2, "Coordena_1": 2064561, "HydroID": "6472350006", "LandElev": -9999}}, {"geometry": {"type": "Point", "coordinates": [-68.88683229918612, 18.672538770753913]}, "type": "Feature", "properties": {"Coordenada": 511934, "AquiferID": 2, "Coordena_1": 2064599, "HydroID": "6472350007", "LandElev": -9999}}, {"geometry": {"type": "Point", "coordinates": [-68.88360794948537, 18.672835053355495]}, "type": "Feature", "properties": {"Coordenada": 512274, "AquiferID": 2, "Coordena_1": 2064632, "HydroID": "6472350008", "LandElev": -9999}}, {"geometry": {"type": "Point", "coordinates": [-68.88627131433677, 18.674788890760663]}, "type": "Feature", "properties": {"Coordenada": 511993, "AquiferID": 2, "Coordena_1": 2064848, "HydroID": "6472350009", "LandElev": -9999}}, {"geometry": {"type": "Point", "coordinates": [-68.88767427882378, 18.675557964231235]}, "type": "Feature", "properties": {"Coordenada": 511845, "AquiferID": 2, "Coordena_1": 2064933, "HydroID": "6472350010", "LandElev": -9999}}, {"TsValue": [-5.53, -3.52, -3.48, -3.11, -3.06, -0.97, -0.98, -1.64, -1.57, -1.99, -0.77, -0.98, -3.05], "TsTime": [1060905600, 1067299200, 1068854400, 1070496000, 1073606400, 1075852800, 1078963200, 1081209600, 1083888000, 1089244800, 1091664000, 1094169600, 1319414400], "geometry": {"type": "Point", "coordinates": [-68.89921865022677, 18.685488222954675]}, "TsValue_norm": [-5.53, -3.52, -3.48, -3.11, -3.06, -0.97, -0.98, -1.64, -1.57, -1.99, -0.77, -0.98, -3.05], "type": "Feature", "properties": {"Coordenada": 510627, "AquiferID": 2, "Coordena_1": 2066031, "HydroID": "6472350012", "LandElev": -9999}}, {"TsValue": [-5.36, -4.28, -4.42, -2.68, -2.6, -1.02, -1.09, -1.01, -0.98, -1.04, -1.18, -1.16], "TsTime": [1060905600, 1067299200, 1068854400, 1070496000, 1073606400, 1075852800, 1078963200, 1081123200, 1083888000, 1089244800, 1091664000, 1094169600], "geometry": {"type": "Point", "coordinates": [-68.87782388307808, 18.672216795739033]}, "TsValue_norm": [-5.36, -4.28, -4.42, -2.68, -2.6, -1.02, -1.09, -1.01, -0.98, -1.04, -1.18, -1.16], "type": "Feature", "properties": {"Coordenada": 512884, "AquiferID": 2, "Coordena_1": 2064564, "HydroID": "6472350014", "LandElev": -9999}}, {"geometry": {"type": "Point", "coordinates": [-68.8768016507811, 18.66957703534363]}, "type": "Feature", "properties": {"Coordenada": 512992, "AquiferID": 2, "Coordena_1": 2064272, "HydroID": "6472350015", "LandElev": -9999}}, {"geometry": {"type": "Point", "coordinates": [-68.8721180183648, 18.668534535652753]}, "type": "Feature", "properties": {"Coordenada": 513486, "AquiferID": 2, "Coordena_1": 2064157, "HydroID": "6472350016", "LandElev": -9999}}, {"TsValue": [-10.38, -6.32, -6.54, -4.65, -4.62, -7.38, -7.89, -6.32, -6.3, -7.2, -4.08, -4.02, -5.15, -4.65, -4.98], "TsTime": [1060905600, 1067299200, 1068854400, 1070496000, 1073606400, 1075852800, 1078963200, 1081123200, 1083801600, 1089244800, 1091664000, 1094169600, 1154995200, 1319414400, 1326240000], "geometry": {"type": "Point", "coordinates": [-68.87213698347625, 18.668534548565916]}, "TsValue_norm": [-10.38, -6.32, -6.54, -4.65, -4.62, -7.38, -7.89, -6.32, -6.3, -7.2, -4.08, -4.02, -5.15, -4.65, -4.98], "type": "Feature", "properties": {"Coordenada": 513484, "AquiferID": 2, "Coordena_1": 2064157, "HydroID": "6472350017", "LandElev": -9999}}, {"geometry": {"type": "Point", "coordinates": [-68.90277302704384, 18.688888378125426]}, "type": "Feature", "properties": {"Coordenada": 510252, "AquiferID": 2, "Coordena_1": 2066407, "HydroID": "6472350018", "LandElev": -9999}}, {"TsValue": [-35.0, -29.33, -29.75, -27.7, -26.09, -31.56, -32.8, -32.06, -32.28, -32.88, -32.6, -32.64], "TsTime": [1060905600, 1067299200, 1068854400, 1070496000, 1073606400, 1075852800, 1078963200, 1081123200, 1083801600, 1089244800, 1091664000, 1094256000], "geometry": {"type": "Point", "coordinates": [-68.82311614451247, 18.673863329540517]}, "TsValue_norm": [-35.0, -29.33, -29.75, -27.7, -26.09, -31.56, -32.8, -32.06, -32.28, -32.88, -32.6, -32.64], "type": "Feature", "properties": {"Coordenada": 518653, "AquiferID": 2, "Coordena_1": 2064751, "HydroID": "6472360001", "LandElev": -9999}}, {"geometry": {"type": "Point", "coordinates": [-68.82865634253383, 18.690525430161976]}, "type": "Feature", "properties": {"Coordenada": 518067, "AquiferID": 2, "Coordena_1": 2066594, "HydroID": "6472360002", "LandElev": -9999}}, {"geometry": {"type": "Point", "coordinates": [-68.80716620741897, 18.698837554285525]}, "type": "Feature", "properties": {"Coordenada": 520332, "AquiferID": 2, "Coordena_1": 2067516, "HydroID": "6472360003", "LandElev": -9999}}, {"geometry": {"type": "Point", "coordinates": [-68.81474649752163, 18.67918765524396]}, "type": "Feature", "properties": {"Coordenada": 519535, "AquiferID": 2, "Coordena_1": 2065341, "HydroID": "6472360004", "LandElev": -9999}}, {"geometry": {"type": "Point", "coordinates": [-68.80831175674858, 18.67535813816777]}, "type": "Feature", "properties": {"Coordenada": 520214, "AquiferID": 2, "Coordena_1": 2064918, "HydroID": "6472360005", "LandElev": -9999}}, {"geometry": {"type": "Point", "coordinates": [-68.82808599283963, 18.682435936777786]}, "type": "Feature", "properties": {"Coordenada": 518128, "AquiferID": 2, "Coordena_1": 2065699, "HydroID": "6472360006", "LandElev": -9999}}, {"geometry": {"type": "Point", "coordinates": [-68.9985087167136, 18.954518164435868]}, "type": "Feature", "properties": {"Coordenada": 500157, "AquiferID": 2, "Coordena_1": 2095795, "HydroID": "6472410001", "LandElev": -9999}}, {"geometry": {"type": "Point", "coordinates": [-68.90336276907192, 18.96807666680038]}, "type": "Feature", "properties": {"Coordenada": 510173, "AquiferID": 2, "Coordena_1": 2097298, "HydroID": "6472420001", "LandElev": -9999}}, {"geometry": {"type": "Point", "coordinates": [-68.87965522138069, 18.964050044357215]}, "type": "Feature", "properties": {"Coordenada": 512669, "AquiferID": 2, "Coordena_1": 2096854, "HydroID": "6472420002", "LandElev": -9999}}, {"geometry": {"type": "Point", "coordinates": [-68.91341892903917, 18.77182572243006]}, "type": "Feature", "properties": {"Coordenada": 509125, "AquiferID": 2, "Coordena_1": 2075583, "HydroID": "6472420005", "LandElev": -9999}}, {"geometry": {"type": "Point", "coordinates": [-68.79874213952174, 18.94779333951348]}, "type": "Feature", "properties": {"Coordenada": 521189, "AquiferID": 2, "Coordena_1": 2095063, "HydroID": "6472430001", "LandElev": -9999}}, {"geometry": {"type": "Point", "coordinates": [-68.80286925069323, 18.959799822857676]}, "type": "Feature", "properties": {"Coordenada": 520753, "AquiferID": 2, "Coordena_1": 2096391, "HydroID": "6472430002", "LandElev": -9999}}, {"geometry": {"type": "Point", "coordinates": [-68.79482848500972, 18.963659222191016]}, "type": "Feature", "properties": {"Coordenada": 521599, "AquiferID": 2, "Coordena_1": 2096819, "HydroID": "6472430003", "LandElev": -9999}}, {"geometry": {"type": "Point", "coordinates": [-68.80105646140188, 18.950525219774597]}, "type": "Feature", "properties": {"Coordenada": 520945, "AquiferID": 2, "Coordena_1": 2095365, "HydroID": "6472430004", "LandElev": -9999}}, {"geometry": {"type": "Point", "coordinates": [-68.9925015174693, 18.832670542425767]}, "type": "Feature", "properties": {"Coordenada": 500790, "AquiferID": 2, "Coordena_1": 2082313, "HydroID": "6472440001", "LandElev": -9999}}, {"geometry": {"type": "Point", "coordinates": [-68.99272886829807, 18.843154449796753]}, "type": "Feature", "properties": {"Coordenada": 500766, "AquiferID": 2, "Coordena_1": 2083473, "HydroID": "6472440002", "LandElev": -9999}}, {"geometry": {"type": "Point", "coordinates": [-68.98897931834739, 18.844320146804577]}, "type": "Feature", "properties": {"Coordenada": 501161, "AquiferID": 2, "Coordena_1": 2083602, "HydroID": "6472440003", "LandElev": -9999}}, {"geometry": {"type": "Point", "coordinates": [-68.98703291949401, 18.850257878575878]}, "type": "Feature", "properties": {"Coordenada": 501366, "AquiferID": 2, "Coordena_1": 2084259, "HydroID": "6472440004", "LandElev": -9999}}, {"TsValue": [-6.7, -4.99, -2.51, -2.26, -2.66, -4.57, -4.61, -4.59, -4.56, -4.39, -4.14, -5.49], "TsTime": [1060905600, 1067385600, 1068854400, 1070496000, 1073865600, 1075852800, 1078963200, 1081123200, 1083801600, 1086912000, 1089244800, 1094256000], "geometry": {"type": "Point", "coordinates": [-68.9862352752671, 18.85337587261595]}, "TsValue_norm": [-6.7, -4.99, -2.51, -2.26, -2.66, -4.57, -4.61, -4.59, -4.56, -4.39, -4.14, -5.49], "type": "Feature", "properties": {"Coordenada": 501450, "AquiferID": 2, "Coordena_1": 2084604, "HydroID": "6472440005", "LandElev": -9999}}, {"geometry": {"type": "Point", "coordinates": [-68.98666221927026, 18.856376462193413]}, "type": "Feature", "properties": {"Coordenada": 501405, "AquiferID": 2, "Coordena_1": 2084936, "HydroID": "6472440006", "LandElev": -9999}}], "aquifermin": -46.0}